{
    "puzzles": [
        {
            "rotation": 5,
            "start": 3583
        },
        {
            "rotation": 0,
            "start": 3318
        },
        {
            "rotation": 1,
            "start": 1873
        },
        {
            "rotation": 4,
            "start": 2858
        },
        {
            "rotation": 5,
            "start": 3457
        },
        {
            "rotation": 3,
            "start": 4892
        },
        {
            "rotation": 1,
            "start": 1819
        },
        {
            "rotation": 5,
            "start": 1315
        },
        {
            "rotation": 4,
            "start": 2714
        },
        {
            "rotation": 5,
            "start": 4183
        },
        {
            "rotation": 6,
            "start": 3458
        },
        {
            "rotation": 1,
            "start": 1531
        },
        {
            "rotation": 5,
            "start": 1164
        },
        {
            "rotation": 1,
            "start": 2688
        },
        {
            "rotation": 2,
            "start": 2861
        },
        {
            "rotation": 3,
            "start": 4196
        },
        {
            "rotation": 6,
            "start": 2714
        },
        {
            "rotation": 3,
            "start": 1886
        },
        {
            "rotation": 5,
            "start": 3318
        },
        {
            "rotation": 0,
            "start": 4902
        },
        {
            "rotation": 1,
            "start": 1812
        },
        {
            "rotation": 2,
            "start": 4901
        },
        {
            "rotation": 3,
            "start": 4092
        },
        {
            "rotation": 4,
            "start": 2692
        },
        {
            "rotation": 5,
            "start": 3156
        },
        {
            "rotation": 3,
            "start": 4166
        },
        {
            "rotation": 6,
            "start": 1996
        },
        {
            "rotation": 1,
            "start": 2592
        },
        {
            "rotation": 4,
            "start": 2665
        },
        {
            "rotation": 1,
            "start": 2570
        },
        {
            "rotation": 5,
            "start": 3115
        },
        {
            "rotation": 0,
            "start": 3317
        },
        {
            "rotation": 1,
            "start": 1890
        },
        {
            "rotation": 2,
            "start": 2592
        },
        {
            "rotation": 2,
            "start": 2611
        },
        {
            "rotation": 6,
            "start": 560
        },
        {
            "rotation": 6,
            "start": 542
        },
        {
            "rotation": 1,
            "start": 1846
        },
        {
            "rotation": 5,
            "start": 2964
        },
        {
            "rotation": 5,
            "start": 2981
        },
        {
            "rotation": 3,
            "start": 4153
        },
        {
            "rotation": 6,
            "start": 572
        },
        {
            "rotation": 1,
            "start": 2012
        }
    ],
    "distance": 15,
    "id": "/5UB",
    "layout": "e+4Q"
}