{
    "puzzles": [
        {
            "rotation": 1,
            "start": 2568
        },
        {
            "rotation": 1,
            "start": 3294
        },
        {
            "rotation": 2,
            "start": 1574
        },
        {
            "rotation": 5,
            "start": 2546
        },
        {
            "rotation": 5,
            "start": 1802
        },
        {
            "rotation": 2,
            "start": 2354
        },
        {
            "rotation": 6,
            "start": 2244
        },
        {
            "rotation": 6,
            "start": 2654
        },
        {
            "rotation": 3,
            "start": 444
        },
        {
            "rotation": 5,
            "start": 3276
        },
        {
            "rotation": 3,
            "start": 566
        },
        {
            "rotation": 5,
            "start": 1692
        },
        {
            "rotation": 6,
            "start": 1500
        },
        {
            "rotation": 6,
            "start": 1994
        },
        {
            "rotation": 5,
            "start": 3198
        },
        {
            "rotation": 5,
            "start": 2472
        },
        {
            "rotation": 1,
            "start": 2856
        },
        {
            "rotation": 1,
            "start": 4896
        },
        {
            "rotation": 1,
            "start": 3582
        },
        {
            "rotation": 1,
            "start": 4782
        },
        {
            "rotation": 6,
            "start": 1092
        },
        {
            "rotation": 6,
            "start": 1154
        },
        {
            "rotation": 2,
            "start": 4819
        },
        {
            "rotation": 2,
            "start": 1813
        },
        {
            "rotation": 2,
            "start": 4896
        },
        {
            "rotation": 2,
            "start": 2593
        },
        {
            "rotation": 3,
            "start": 2593
        },
        {
            "rotation": 3,
            "start": 2597
        },
        {
            "rotation": 3,
            "start": 2716
        },
        {
            "rotation": 3,
            "start": 2715
        }
    ],
    "distance": 14,
    "id": "3+4D",
    "layout": "f+Yc"
}