{
    "puzzles": [
        {
            "rotation": 0,
            "start": 266
        },
        {
            "rotation": 0,
            "start": 396
        },
        {
            "rotation": 0,
            "start": 518
        },
        {
            "rotation": 3,
            "start": 477
        },
        {
            "rotation": 4,
            "start": 697
        },
        {
            "rotation": 3,
            "start": 356
        },
        {
            "rotation": 3,
            "start": 234
        },
        {
            "rotation": 1,
            "start": 29
        },
        {
            "rotation": 5,
            "start": 566
        },
        {
            "rotation": 3,
            "start": 691
        },
        {
            "rotation": 3,
            "start": 666
        },
        {
            "rotation": 4,
            "start": 314
        },
        {
            "rotation": 1,
            "start": 111
        },
        {
            "rotation": 1,
            "start": 67
        },
        {
            "rotation": 5,
            "start": 557
        },
        {
            "rotation": 4,
            "start": 211
        },
        {
            "rotation": 5,
            "start": 595
        },
        {
            "rotation": 3,
            "start": 618
        },
        {
            "rotation": 4,
            "start": 672
        },
        {
            "rotation": 4,
            "start": 676
        },
        {
            "rotation": 4,
            "start": 692
        },
        {
            "rotation": 5,
            "start": 444
        },
        {
            "rotation": 4,
            "start": 553
        },
        {
            "rotation": 2,
            "start": 134
        },
        {
            "rotation": 4,
            "start": 303
        },
        {
            "rotation": 1,
            "start": 192
        },
        {
            "rotation": 5,
            "start": 435
        },
        {
            "rotation": 1,
            "start": 252
        },
        {
            "rotation": 4,
            "start": 181
        },
        {
            "rotation": 2,
            "start": 536
        },
        {
            "rotation": 5,
            "start": 478
        },
        {
            "rotation": 1,
            "start": 211
        },
        {
            "rotation": 1,
            "start": 355
        },
        {
            "rotation": 2,
            "start": 314
        },
        {
            "rotation": 1,
            "start": 156
        },
        {
            "rotation": 1,
            "start": 318
        },
        {
            "rotation": 3,
            "start": 469
        },
        {
            "rotation": 1,
            "start": 196
        },
        {
            "rotation": 3,
            "start": 444
        },
        {
            "rotation": 5,
            "start": 292
        },
        {
            "rotation": 1,
            "start": 362
        },
        {
            "rotation": 1,
            "start": 461
        },
        {
            "rotation": 1,
            "start": 170
        },
        {
            "rotation": 5,
            "start": 313
        },
        {
            "rotation": 3,
            "start": 687
        },
        {
            "rotation": 3,
            "start": 566
        },
        {
            "rotation": 3,
            "start": 174
        },
        {
            "rotation": 5,
            "start": 291
        },
        {
            "rotation": 5,
            "start": 325
        },
        {
            "rotation": 5,
            "start": 317
        },
        {
            "rotation": 5,
            "start": 304
        },
        {
            "rotation": 1,
            "start": 432
        },
        {
            "rotation": 3,
            "start": 366
        },
        {
            "rotation": 1,
            "start": 204
        },
        {
            "rotation": 3,
            "start": 125
        },
        {
            "rotation": 1,
            "start": 256
        },
        {
            "rotation": 4,
            "start": 647
        },
        {
            "rotation": 3,
            "start": 702
        },
        {
            "rotation": 4,
            "start": 506
        },
        {
            "rotation": 1,
            "start": 382
        },
        {
            "rotation": 1,
            "start": 248
        },
        {
            "rotation": 3,
            "start": 322
        },
        {
            "rotation": 4,
            "start": 526
        },
        {
            "rotation": 1,
            "start": 410
        },
        {
            "rotation": 4,
            "start": 396
        },
        {
            "rotation": 4,
            "start": 266
        },
        {
            "rotation": 4,
            "start": 278
        },
        {
            "rotation": 4,
            "start": 265
        },
        {
            "rotation": 1,
            "start": 374
        },
        {
            "rotation": 3,
            "start": 414
        },
        {
            "rotation": 1,
            "start": 300
        },
        {
            "rotation": 3,
            "start": 576
        },
        {
            "rotation": 5,
            "start": 78
        },
        {
            "rotation": 5,
            "start": 60
        },
        {
            "rotation": 5,
            "start": 56
        },
        {
            "rotation": 5,
            "start": 86
        },
        {
            "rotation": 5,
            "start": 55
        },
        {
            "rotation": 3,
            "start": 288
        },
        {
            "rotation": 4,
            "start": 373
        },
        {
            "rotation": 4,
            "start": 382
        },
        {
            "rotation": 5,
            "start": 82
        },
        {
            "rotation": 3,
            "start": 532
        },
        {
            "rotation": 4,
            "start": 134
        },
        {
            "rotation": 5,
            "start": 107
        }
    ],
    "distance": 10,
    "id": "/w8=",
    "layout": "/0c="
}