{
    "puzzles": [
        {
            "rotation": 0,
            "start": 2426
        },
        {
            "rotation": 6,
            "start": 4166
        },
        {
            "rotation": 1,
            "start": 831
        },
        {
            "rotation": 2,
            "start": 5009
        },
        {
            "rotation": 3,
            "start": 3151
        },
        {
            "rotation": 4,
            "start": 743
        },
        {
            "rotation": 5,
            "start": 4559
        },
        {
            "rotation": 6,
            "start": 415
        },
        {
            "rotation": 5,
            "start": 806
        }
    ],
    "distance": 15,
    "id": "T5YB",
    "old_id": "000001010010001111111",
    "layout": "T8YQ"
}