{
    "puzzles": [
        {
            "rotation": 3,
            "start": 453
        },
        {
            "rotation": 2,
            "start": 1576
        },
        {
            "rotation": 0,
            "start": 3318
        },
        {
            "rotation": 6,
            "start": 4367
        },
        {
            "rotation": 0,
            "start": 4040
        },
        {
            "rotation": 3,
            "start": 693
        },
        {
            "rotation": 1,
            "start": 1819
        },
        {
            "rotation": 1,
            "start": 1903
        },
        {
            "rotation": 1,
            "start": 3535
        },
        {
            "rotation": 1,
            "start": 4735
        },
        {
            "rotation": 4,
            "start": 2714
        },
        {
            "rotation": 2,
            "start": 1575
        },
        {
            "rotation": 4,
            "start": 4040
        },
        {
            "rotation": 2,
            "start": 2861
        },
        {
            "rotation": 2,
            "start": 4540
        },
        {
            "rotation": 3,
            "start": 4196
        },
        {
            "rotation": 3,
            "start": 445
        },
        {
            "rotation": 3,
            "start": 449
        },
        {
            "rotation": 5,
            "start": 1685
        },
        {
            "rotation": 4,
            "start": 2810
        },
        {
            "rotation": 4,
            "start": 2692
        },
        {
            "rotation": 4,
            "start": 2708
        },
        {
            "rotation": 6,
            "start": 2063
        },
        {
            "rotation": 1,
            "start": 2592
        },
        {
            "rotation": 2,
            "start": 1812
        },
        {
            "rotation": 5,
            "start": 3115
        },
        {
            "rotation": 2,
            "start": 2592
        },
        {
            "rotation": 0,
            "start": 3478
        },
        {
            "rotation": 0,
            "start": 4318
        },
        {
            "rotation": 0,
            "start": 3807
        },
        {
            "rotation": 1,
            "start": 4018
        },
        {
            "rotation": 3,
            "start": 2714
        },
        {
            "rotation": 6,
            "start": 520
        },
        {
            "rotation": 6,
            "start": 572
        }
    ],
    "distance": 15,
    "id": "vuYD",
    "old_id": "001011100110111110110",
    "layout": "N+4Y"
}