{
    "puzzles": [
        {
            "rotation": 4,
            "start": 107
        },
        {
            "rotation": 4,
            "start": 119
        },
        {
            "rotation": 5,
            "start": 518
        },
        {
            "rotation": 5,
            "start": 566
        },
        {
            "rotation": 6,
            "start": 3054
        },
        {
            "rotation": 6,
            "start": 3294
        },
        {
            "rotation": 0,
            "start": 141
        },
        {
            "rotation": 0,
            "start": 1581
        },
        {
            "rotation": 1,
            "start": 713
        },
        {
            "rotation": 2,
            "start": 4863
        },
        {
            "rotation": 3,
            "start": 2305
        },
        {
            "rotation": 3,
            "start": 2309
        }
    ],
    "distance": 22,
    "id": "bI8B",
    "layout": "N8YI"
}