{
    "nodes": 7,
    "edges": [
        [
            0,
            1
        ],
        [
            0,
            6
        ],
        [
            1,
            2
        ],
        [
            2,
            3
        ],
        [
            3,
            4
        ],
        [
            4,
            5
        ],
        [
            5,
            6
        ]
    ],
    "puzzles": [
        {
            "beads": [
                4,
                5,
                6,
                1,
                2,
                3
            ],
            "rotation": 0
        }
    ],
    "distance": 21
}