{
    "puzzles": [
        {
            "rotation": 4,
            "start": 475
        },
        {
            "rotation": 1,
            "start": 415
        },
        {
            "rotation": 2,
            "start": 143
        },
        {
            "rotation": 5,
            "start": 572
        },
        {
            "rotation": 3,
            "start": 719
        },
        {
            "rotation": 0,
            "start": 316
        },
        {
            "rotation": 4,
            "start": 415
        },
        {
            "rotation": 1,
            "start": 475
        },
        {
            "rotation": 2,
            "start": 572
        },
        {
            "rotation": 5,
            "start": 143
        },
        {
            "rotation": 3,
            "start": 316
        },
        {
            "rotation": 0,
            "start": 719
        }
    ],
    "distance": 15,
    "id": "+A0=",
    "layout": "Zi4="
}